graphene_pydantic/__init__.py
graphene_pydantic/converters.py
graphene_pydantic/inputobjecttype.py
graphene_pydantic/objecttype.py
graphene_pydantic/registry.py
graphene_pydantic/util.py
graphene_pydantic-0.6.0.dist-info/LICENSE.md
graphene_pydantic-0.6.0.dist-info/METADATA
graphene_pydantic-0.6.0.dist-info/WHEEL
graphene_pydantic-0.6.0.dist-info/RECORD
