Metadata-Version: 2.1
Name: graphene_pydantic
Version: 0.6.0
Summary: Graphene Pydantic integration
Home-page: https://github.com/graphql-python/graphene-pydantic
License: Apache-2.0
Keywords: api,graphql,protocol,rest,relay,graphene,pydantic,model
Author: Rami Chowdhury
Author-email: rami.chowdhury@gmail.com
Requires-Python: >=3.8,<4.0
Classifier: Development Status :: 3 - Alpha
Classifier: Intended Audience :: Developers
Classifier: License :: OSI Approved :: Apache Software License
Classifier: Programming Language :: Python :: 3
Classifier: Programming Language :: Python :: 3.8
Classifier: Programming Language :: Python :: 3.9
Classifier: Programming Language :: Python :: 3.10
Classifier: Programming Language :: Python :: 3.11
Classifier: Programming Language :: Python :: 3.12
Classifier: Programming Language :: Python :: Implementation :: PyPy
Classifier: Topic :: Software Development :: Libraries
Requires-Dist: graphene (>=2.1.8)
Requires-Dist: pydantic (>=2.0)
Project-URL: Repository, https://github.com/graphql-python/graphene-pydantic
